copul/__init__.py
copul/basictools.py
copul/chatterjee.py
copul/copula_sampler.py
copul/data_uniformer.py
copul/exceptions.py
copul/family_list.py
copul/foci.py
copul/numerics.py
copul/star_product.py
copul/checkerboard/__init__.py
copul/checkerboard/bernstein.py
copul/checkerboard/biv_bernstein.py
copul/checkerboard/biv_block_diag_mixed.py
copul/checkerboard/biv_check_min.py
copul/checkerboard/biv_check_mixed.py
copul/checkerboard/biv_check_pi.py
copul/checkerboard/biv_check_w.py
copul/checkerboard/check.py
copul/checkerboard/check_min.py
copul/checkerboard/check_pi.py
copul/checkerboard/checkerboarder.py
copul/checkerboard/matrix.py
copul/checkerboard/shuffle_min.py
copul/docs/.gitkeep
copul/docs/rank_correlation_estimates/AliMikhailHaqData.pkl
copul/docs/rank_correlation_estimates/BB5Data.pkl
copul/docs/rank_correlation_estimates/BivClayton Copula_data.pkl
copul/docs/rank_correlation_estimates/BivClaytonData.pkl
copul/docs/rank_correlation_estimates/ClaytonData.pkl
copul/docs/rank_correlation_estimates/CuadrasAugeData.pkl
copul/docs/rank_correlation_estimates/FarlieGumbelMorgensternData.pkl
copul/docs/rank_correlation_estimates/Frank Copula_data.pkl
copul/docs/rank_correlation_estimates/FrankData.pkl
copul/docs/rank_correlation_estimates/FrechetData.pkl
copul/docs/rank_correlation_estimates/GalambosData.pkl
copul/docs/rank_correlation_estimates/Gaussian Copula_data.pkl
copul/docs/rank_correlation_estimates/GaussianData.pkl
copul/docs/rank_correlation_estimates/GenestGhoudiData.pkl
copul/docs/rank_correlation_estimates/GumbelBarnettData.pkl
copul/docs/rank_correlation_estimates/GumbelHougaard Copula_data.pkl
copul/docs/rank_correlation_estimates/GumbelHougaardData.pkl
copul/docs/rank_correlation_estimates/HueslerReissData.pkl
copul/docs/rank_correlation_estimates/Joe Copula_data.pkl
copul/docs/rank_correlation_estimates/JoeData.pkl
copul/docs/rank_correlation_estimates/JoeEVData.pkl
copul/docs/rank_correlation_estimates/LaplaceData.pkl
copul-0.3.8.dist-info/METADATA
copul-0.3.8.dist-info/WHEEL
copul-0.3.8.dist-info/licenses/LICENSE
copul-0.3.8.dist-info/RECORD
