Metadata-Version: 2.4
Name: copul
Version: 0.3.8
Summary: A Python package for copula analysis and computation.
Project-URL: Repository, https://github.com/Corrram/copul
Project-URL: Documentation, https://copul.readthedocs.io
Project-URL: Issue Tracker, https://github.com/Corrram/copul/issues
Author-email: Marcus Rockel <marcus.rockel@finance.uni-freiburg.de>
License-File: LICENSE
Classifier: Operating System :: OS Independent
Classifier: Programming Language :: Python :: 3
Requires-Python: >=3.10
Requires-Dist: matplotlib>=3.9
Requires-Dist: numpy>=2.0
Requires-Dist: pandas>=2.3
Requires-Dist: scipy>=1.14
Requires-Dist: statsmodels>=0.14
Requires-Dist: sympy-plot-backends>=3.1
Requires-Dist: sympy>=1.14
Requires-Dist: typing-extensions>=4.15.0
Provides-Extra: dev
Requires-Dist: black>=24.8; extra == 'dev'
Requires-Dist: build>=0.10.0; extra == 'dev'
Requires-Dist: cvxpy>=1.7.1; extra == 'dev'
Requires-Dist: hatchling>=1.27.0; extra == 'dev'
Requires-Dist: jupyter>=1.0.0; extra == 'dev'
Requires-Dist: mypy>=1.0.0; extra == 'dev'
Requires-Dist: pylint>=2.17.0; extra == 'dev'
Requires-Dist: pytest-cov>=5.0.0; extra == 'dev'
Requires-Dist: pytest-xdist>=3.6.1; extra == 'dev'
Requires-Dist: pytest>=8.3.5; extra == 'dev'
Requires-Dist: ruff>=0.9.9; extra == 'dev'
Requires-Dist: seaborn>=0.13.2; extra == 'dev'
Requires-Dist: sphinx-rtd-theme>=2.0; extra == 'dev'
Requires-Dist: sphinx>=7.4; extra == 'dev'
Requires-Dist: twine>=6.1.0; extra == 'dev'
